pytecplot-1.7.3.dist-info/licenses/LICENSE.html
tecplot/__init__.py
tecplot/constant.py
tecplot/exception.py
tecplot/macro.py
tecplot/version.py
tecplot/annotation/__init__.py
tecplot/annotation/annotation.py
tecplot/annotation/geometry.py
tecplot/annotation/georeference.py
tecplot/annotation/image.py
tecplot/annotation/iter.py
tecplot/annotation/polyline.py
tecplot/annotation/text.py
tecplot/data/__init__.py
tecplot/data/array.py
tecplot/data/create.py
tecplot/data/dataset.py
tecplot/data/extract.py
tecplot/data/face_neighbors.py
tecplot/data/facemap.py
tecplot/data/fe_cell_type.py
tecplot/data/load.py
tecplot/data/nodemap.py
tecplot/data/operate.py
tecplot/data/query.py
tecplot/data/save.py
tecplot/data/variable.py
tecplot/data/zone.py
tecplot/export/__init__.py
tecplot/export/animation.py
tecplot/export/export_setup.py
tecplot/export/image.py
tecplot/export/print_setup.py
tecplot/export/time_animation.py
tecplot/extension/__init__.py
tecplot/extension/ipython.py
tecplot/layout/__init__.py
tecplot/layout/frame.py
tecplot/layout/layout.py
tecplot/layout/page.py
tecplot/legend/__init__.py
tecplot/legend/contour_legend.py
tecplot/legend/legend.py
tecplot/legend/line_legend.py
tecplot/legend/rgb_coloring_legend.py
tecplot/legend/scatter_legend.py
tecplot/plot/__init__.py
tecplot/plot/axes.py
tecplot/plot/axis.py
tecplot/plot/blanking.py
tecplot/plot/contour.py
tecplot/plot/effects.py
tecplot/plot/fieldmap.py
tecplot/plot/grid.py
tecplot/plot/hoe_settings.py
tecplot/plot/isosurface.py
tecplot/plot/labels.py
tecplot/plot/linemap.py
tecplot/plot/linking.py
tecplot/plot/plot.py
tecplot/plot/rgb_coloring.py
tecplot/plot/scatter.py
tecplot/plot/slice.py
tecplot/plot/streamtrace.py
tecplot/plot/symbol.py
tecplot/plot/ticks.py
tecplot/plot/title.py
tecplot/plot/vector.py
tecplot/plot/view.py
tecplot/session/__init__.py
tecplot/session/aux_data.py
tecplot/session/config.py
tecplot/session/session.py
tecplot/session/state_changed.py
tecplot/session/style.py
tecplot/tecutil/__init__.py
tecplot/tecutil/arglist.py
pytecplot-1.7.3.dist-info/METADATA
pytecplot-1.7.3.dist-info/WHEEL
pytecplot-1.7.3.dist-info/top_level.txt
pytecplot-1.7.3.dist-info/RECORD
