Metadata-Version: 2.4
Name: pytecplot
Version: 1.7.3
Summary: A Python interface to Tecplot 360
Author-email: "Tecplot, Inc." <support@tecplot.com>
License-Expression: LicenseRef-Tecplot-Software-License
Project-URL: homepage, https://www.tecplot.com/docs/pytecplot
Keywords: tecplot,cfd,data analysis,scientific,scientific computing,statistics,visualization,numerical simulation,aerospace
Classifier: Development Status :: 5 - Production/Stable
Classifier: Intended Audience :: Developers
Classifier: Intended Audience :: Education
Classifier: Intended Audience :: End Users/Desktop
Classifier: Intended Audience :: Science/Research
Classifier: Natural Language :: English
Classifier: Operating System :: OS Independent
Classifier: Topic :: Education
Classifier: Topic :: Multimedia :: Graphics :: 3D Rendering
Classifier: Topic :: Multimedia :: Graphics :: Presentation
Classifier: Topic :: Multimedia :: Graphics :: Viewers
Classifier: Topic :: Scientific/Engineering
Classifier: Topic :: Scientific/Engineering :: Information Analysis
Classifier: Topic :: Scientific/Engineering :: Mathematics
Classifier: Topic :: Scientific/Engineering :: Physics
Classifier: Topic :: Scientific/Engineering :: Visualization
Classifier: Topic :: Software Development :: Libraries
Classifier: Topic :: Software Development :: Libraries :: Python Modules
Classifier: Programming Language :: Python
Classifier: Programming Language :: Python :: 3
Classifier: Programming Language :: Python :: 3.12
Classifier: Programming Language :: Python :: 3.13
Classifier: Programming Language :: Python :: 3.14
Requires-Python: >=3.8
License-File: LICENSE.html
Requires-Dist: protobuf>=3.20.0
Requires-Dist: pyzmq
Provides-Extra: extras
Requires-Dist: ipython; extra == "extras"
Requires-Dist: numpy; extra == "extras"
Requires-Dist: pillow; extra == "extras"
Provides-Extra: doc
Requires-Dist: sphinx; extra == "doc"
Requires-Dist: pyyaml; extra == "doc"
Provides-Extra: test
Requires-Dist: ipython; extra == "test"
Requires-Dist: numpy; extra == "test"
Requires-Dist: pillow; extra == "test"
Requires-Dist: coverage; extra == "test"
Requires-Dist: scipy; extra == "test"
Requires-Dist: tox; extra == "test"
Requires-Dist: filetype; extra == "test"
Provides-Extra: all
Requires-Dist: ipython; extra == "all"
Requires-Dist: numpy; extra == "all"
Requires-Dist: pillow; extra == "all"
Requires-Dist: sphinx; extra == "all"
Requires-Dist: pyyaml; extra == "all"
Requires-Dist: coverage; extra == "all"
Requires-Dist: scipy; extra == "all"
Requires-Dist: tox; extra == "all"
Dynamic: license-file
